xspace/__init__.py
xspace/api.py
xspace/chat_extractor.py
xspace/cookies.py
xspace/main.py
xspace/xspace.py
xspace/xspace_dl.py
xspace_dl-0.3.13.dist-info/LICENSE
xspace_dl-0.3.13.dist-info/METADATA
xspace_dl-0.3.13.dist-info/WHEEL
xspace_dl-0.3.13.dist-info/entry_points.txt
xspace_dl-0.3.13.dist-info/top_level.txt
xspace_dl-0.3.13.dist-info/RECORD
