Metadata-Version: 2.1
Name: xspace-dl
Version: 0.3.13
Summary: A python module to download Twitter spaces
Home-page: https://github.com/rosebabaganoush/xspace-dl
Author: Your Name
Author-email: your.email@example.com
Classifier: Programming Language :: Python :: 3
Classifier: License :: OSI Approved :: GNU General Public License v2 (GPLv2)
Classifier: Operating System :: OS Independent
Requires-Python: >=3.6
License-File: LICENSE
Requires-Dist: requests
Requires-Dist: mutagen
